<?xml version="1.0" encoding="UTF-8" ?>
<!DOCTYPE mapper
        PUBLIC "-//mybatis.org//DTD Mapper 3.0//EN"
        "http://mybatis.org/dtd/mybatis-3-mapper.dtd">
<mapper namespace="com.marler.teammap.mapper.PlayerMapper">

    <!-- 插入球员 -->
    <insert id="insert" useGeneratedKeys="true" keyProperty="id">
        INSERT INTO player (user_id, tm_id, jersey_name, jersey_number, position)
        VALUES (#{userId}, #{tmId}, #{jerseyName}, #{jerseyNumber}, #{position})
    </insert>

    <!-- 根据ID查询球员 -->
    <select id="selectById" resultType="com.marler.teammap.pojo.Player">
        SELECT * FROM player WHERE id = #{id}
    </select>

    <!-- 查询球员详细信息（v_player_info） -->
    <select id="selectPlayerInfoById"
            resultType="com.marler.teammap.dto.response.PlayerInfoVO">
        SELECT
            player_id AS playerId,
            user_id AS userId,
            team_id AS teamId,
            team_name AS teamName,
            team_short_name AS teamShortName,
            team_logo AS teamLogo,
            sport_type AS sportType,
            sport_type_name AS sportTypeName,
            team_gender AS teamGender,
            team_gender_name AS teamGenderName,
            team_description AS teamDescription,
            member_id AS memberId,
            role,
            role_name AS roleName,
            portrait_photo AS portraitPhoto,
            join_time AS joinTime,
            member_update_time AS memberUpdateTime,
            jersey_name AS jerseyName,
            jersey_number AS jerseyNumber,
            position,
            status,
            status_name AS statusName,
            player_create_time AS playerCreateTime,
            player_update_time AS playerUpdateTime
        FROM v_player_info
        WHERE player_id = #{playerId}
    </select>

    <!-- 根据球队ID查询所有球员信息 -->
    <select id="selectPlayerInfoByTeamId"
            resultType="com.marler.teammap.dto.response.PlayerInfoVO">
        SELECT
            player_id AS playerId,
            user_id AS userId,
            team_id AS teamId,
            team_name AS teamName,
            team_short_name AS teamShortName,
            team_logo AS teamLogo,
            sport_type AS sportType,
            sport_type_name AS sportTypeName,
            team_gender AS teamGender,
            team_gender_name AS teamGenderName,
            team_description AS teamDescription,
            member_id AS memberId,
            role,
            role_name AS roleName,
            portrait_photo AS portraitPhoto,
            join_time AS joinTime,
            member_update_time AS memberUpdateTime,
            jersey_name AS jerseyName,
            jersey_number AS jerseyNumber,
            position,
            status,
            status_name AS statusName,
            player_create_time AS playerCreateTime,
            player_update_time AS playerUpdateTime
        FROM v_player_info
        WHERE team_id = #{teamId}
        ORDER BY role ASC, jersey_number ASC
    </select>

</mapper>
